<?xml version="1.0" encoding="ISO-8859-1"?>

<process-definition xmlns="urn:jbpm.org:jpdl-3.2" name="(SG) Controle de prazos de ofícios">
    <description><![CDATA[Código do fluxo: SG_CONTPRAZOS_OFI

Descrição: Gestão de recebimento/prazos de ofícios.

Raia        Localização              Papel
Secretaria  Secretaria Segundo Grau  Chefe de Secretaria
Secretaria  Secretaria Segundo Grau  Servidor Geral]]></description>  
    <!-- SWIMLANES -->
    <swimlane name="Nó de Desvio - (SG) Controle de prazos de ofícios">
        <assignment actor-id="#{actor.id}"/>
    </swimlane>
    <swimlane name="Secretaria">
        <assignment pooled-actors="#{localizacaoAssignment.getPooledActors('602:1338,602:5483')}" actor-id="#{actor.id}"/>
    </swimlane>  
    <!-- START-STATE -->
    <start-state name="Início">
        <task name="Tarefa inicial" swimlane="Secretaria"/>
        <transition to="(SG) Separação em controle de prazos de ofícios" name="(SG) Separação em controle de prazos de ofícios"/>
    </start-state>  
    <!-- NODES -->
    <fork name="(SG) Separação em controle de prazos de ofícios">
        <transition to="(SG) É correios?" name="(SG) É correios?"/>
        <transition to="(SG) É mandado?" name="(SG) É mandado?"/>
    </fork>
    <decision expression="#{entityManager.createQuery(&quot;SELECT COUNT(*) FROM ProcessoParteExpediente AS ppe JOIN ppe.processoExpediente AS pe WHERE ppe.processoJudicial.idProcessoTrf = :idProcessoTrf AND pe.tipoProcessoDocumento.idTipoProcessoDocumento = 34 AND pe.meioExpedicaoExpediente = 'C' AND ppe.dtCienciaParte IS NULL AND ppe.fechado = false&quot;).setParameter(&quot;idProcessoTrf&quot;, tramitacaoProcessualService.recuperaProcesso().idProcessoTrf).getSingleResult() &gt; 0 ? '(SG) Existe registro do processo na tarefa de aguardar AR?' : '(SG) Separação em ofício com ou sem prazo'}" name="(SG) É correios?">
        <transition to="(SG) Separação em ofício com ou sem prazo" name="(SG) Separação em ofício com ou sem prazo"/>
        <transition to="(SG) Existe registro do processo na tarefa de aguardar AR?" name="(SG) Existe registro do processo na tarefa de aguardar AR?"/>
    </decision>
    <decision expression="#{entityManager.createQuery(&quot;SELECT COUNT(*) FROM SituacaoProcesso AS s WHERE s.nomeTarefa = '(SG) Ofício pendente de confirmação do recebimento - REGISTRAR' AND s.processoTrf.idProcessoTrf = :idProcessoTrf&quot;).setParameter(&quot;idProcessoTrf&quot;, tramitacaoProcessualService.recuperaProcesso().idProcessoTrf).getSingleResult() &gt; 0 ? '(SG) Separação em ofício com ou sem prazo' : '(SG) Ofício pendente de confirmação do recebimento - REGISTRAR'}" name="(SG) Existe registro do processo na tarefa de aguardar AR?">
        <transition to="(SG) Separação em ofício com ou sem prazo" name="(SG) Separação em ofício com ou sem prazo"/>
        <transition to="(SG) Ofício pendente de confirmação do recebimento - REGISTRAR" name="(SG) Ofício pendente de confirmação do recebimento - REGISTRAR"/>
    </decision>
    <task-node end-tasks="true" name="(SG) Ofício pendente de devolução do AR - AGUARDAR">
        <task name="(SG) Ofício pendente de devolução do AR - AGUARDAR" swimlane="Secretaria">
            <controller>
                <variable name="aviso1" mapped-name="textAlert:aviso1" access="read,write"/>
                <variable name="WEB-INF_xhtml_flx_exped_controleCorreios" mapped-name="frame:WEB-INF_xhtml_flx_exped_controleCorreios" access="read,write"/>
            </controller>
        </task>
        <description><![CDATA[*Variáveis*

1. aviso1 
   Label: No caso de envio pelo Hermes, informe no campo abaixo o código de envio do Hermes, após obter a confirmação de leitura, prossiga através da opção "Registrar o recebimento".
   Escrita: Sim
   Obrig.: Não
   Tipo: Aviso.

2. Variável: WEB-INF_xhtml_flx_exped_controleCorreios
   Label:
   Escrita: Sim
   Obrig.: Não
   Tipo: Frame]]></description>
        <transition to="Nó de Desvio - (SG) Controle de prazos de ofícios" name="Nó de Desvio - (SG) Controle de prazos de ofícios">
            <condition expression="#{true}"/>
        </transition>
        <transition to="(SG) Ofício pendente de devolução do AR - REGISTRAR" name="Registrar o recebimento"/>
        <transition to="(SG) Junção em controle de prazos de ofícios" name="Cancelar e sair da tarefa"/>
        <event type="task-assign">
            <action expression="#{tramitacaoProcessualService.gravaVariavel('comunicacaoProcessualAction:idsExpedientes', entityManager.createNativeQuery(&quot;select string_agg(cast(pe.id_processo_expediente as text), ',') from tb_processo_expediente pe where pe.in_meio_expedicao_expediente = 'C' and pe.id_processo_trf = &quot;.concat(tramitacaoProcessualService.recuperaProcesso().idProcessoTrf)).getSingleResult().toString())}"/>
        </event>
        <event type="task-create">
            <action expression="#{tramitacaoProcessualService.gravaVariavelTarefa('pje:fluxo:correios:registroCiencia', false)}"/>
        </event>
        <event type="task-end">
            <action expression="#{tramitacaoProcessualService.apagaVariavelTarefa('pje:fluxo:correios:registroCiencia')}"/>
        </event>
    </task-node>
    <task-node end-tasks="true" name="(SG) Ofício pendente de devolução do AR - REGISTRAR">
        <task name="(SG) Ofício pendente de devolução do AR - REGISTRAR" swimlane="Secretaria">
            <controller>
                <variable name="WEB-INF_xhtml_flx_exped_controleCorreios" mapped-name="frame:WEB-INF_xhtml_flx_exped_controleCorreios" access="read,write"/>
            </controller>
        </task>
        <description><![CDATA[*Variáveis*

1. Variável: WEB-INF_xhtml_flx_exped_controleCorreios
   Label:
   Escrita: Sim
   Obrig.: Não
   Tipo: Frame]]></description>
        <transition to="Nó de Desvio - (SG) Controle de prazos de ofícios" name="Nó de Desvio - (SG) Controle de prazos de ofícios">
            <condition expression="#{true}"/>
        </transition>
        <transition to="(SG) Separação em ofício com ou sem prazo" name="Verificar existência de prazo"/>
        <transition to="(SG) Ofício pendente de devolução do AR - AGUARDAR" name="Retornar para aguardar devolução do AR"/>
        <transition to="(SG) Junção em controle de prazos de ofícios" name="Cancelar e sair da tarefa"/>
        <event type="task-create">
            <action expression="#{tramitacaoProcessualService.gravaVariavelTarefa('pje:fluxo:correios:edicaoNumeroAR', false)}"/>
            <action expression="#{tramitacaoProcessualService.gravaVariavelTarefa('frameDefaultLeavingTransition', 'Verificar existência de prazo')}"/>
        </event>
        <event type="task-end">
            <action expression="#{tramitacaoProcessualService.apagaVariavelTarefa('pje:fluxo:correios:edicaoNumeroAR')}"/>
            <action expression="#{tramitacaoProcessualService.apagaVariavelTarefa('frameDefaultLeavingTransition')}"/>
        </event>
    </task-node>
    <task-node end-tasks="true" name="(SG) Ofício pendente de confirmação do recebimento - REGISTRAR">
        <task name="(SG) Ofício pendente de confirmação do recebimento - REGISTRAR" swimlane="Secretaria">
            <controller>
                <variable name="aviso1" mapped-name="textAlert:aviso1" access="read,write"/>
                <variable name="WEB-INF_xhtml_flx_exped_controleCorreios" mapped-name="frame:WEB-INF_xhtml_flx_exped_controleCorreios" access="read,write"/>
                <variable name="aviso2" mapped-name="textAlert:aviso2" access="read,write"/>
            </controller>
        </task>
        <description><![CDATA[*Variáveis*

1. aviso1
   Label: Nos casos de encaminhamento pelo Hermes: Informe no campo abaixo o código de envio do Hermes e clique em "Gravar".
   Escrita: Sim
   Obrig.: Não
   Tipo: Aviso

2. WEB-INF_xhtml_flx_exped_controleCorreios
   Label: 
   Escrita: Sim
   Obrig.: Não
   Tipo: Frame

3. aviso1
   Label: - Após obter a confirmação de leitura, selecione a opção "Registrar Resultado" e anexe o recibo. Caso o resultado seja "Recebido", a contagem do respectivo prazo será iniciada.
   Escrita: Sim
   Obrig.: Não
   Tipo: Aviso]]></description>
        <transition to="Nó de Desvio - (SG) Controle de prazos de ofícios" name="Nó de Desvio - (SG) Controle de prazos de ofícios">
            <condition expression="#{true}"/>
        </transition>
        <transition to="(SG) Há registros pendentes de confirmação de recebimento?" name="Todos os registros concluídos! Verificar existência de prazo"/>
        <transition to="(SG) Junção em controle de prazos de ofícios" name="Cancelar e sair da tarefa"/>
        <event type="task-assign">
            <action expression="#{tramitacaoProcessualService.gravaVariavel('comunicacaoProcessualAction:idsExpedientes', entityManager.createNativeQuery(&quot;select string_agg(cast(pe.id_processo_expediente as text), ',') from tb_processo_expediente pe where pe.in_meio_expedicao_expediente = 'C' and pe.id_processo_trf = &quot;.concat(tramitacaoProcessualService.recuperaProcesso().idProcessoTrf)).getSingleResult().toString())}"/>
        </event>
        <event type="task-create">
            <action expression="#{tramitacaoProcessualService.gravaVariavelTarefa('frameDefaultLeavingTransition', 'Verificar existência de prazo')}"/>
        </event>
        <event type="task-end">
            <action expression="#{tramitacaoProcessualService.apagaVariavelTarefa('frameDefaultLeavingTransition')}"/>
        </event>
    </task-node>
    <decision expression="#{entityManager.createQuery(&quot;SELECT COUNT(*) FROM ProcessoParteExpediente AS ppe JOIN ppe.processoExpediente AS pe WHERE ppe.processoJudicial.idProcessoTrf = :idProcessoTrf AND pe.tipoProcessoDocumento.idTipoProcessoDocumento = 34 AND pe.meioExpedicaoExpediente = 'C' AND ppe.dtCienciaParte IS NULL AND ppe.fechado = false&quot;).setParameter(&quot;idProcessoTrf&quot;, tramitacaoProcessualService.recuperaProcesso().idProcessoTrf).getSingleResult() &gt; 0 ? '(SG) Ofício pendente de confirmação do recebimento - REGISTRAR' : '(SG) Separação em ofício com ou sem prazo'}" name="(SG) Há registros pendentes de confirmação de recebimento?">
        <transition to="(SG) Ofício pendente de confirmação do recebimento - REGISTRAR" name="(SG) Ofício pendente de confirmação do recebimento - REGISTRAR"/>
        <transition to="(SG) Separação em ofício com ou sem prazo" name="(SG) Separação em ofício com ou sem prazo"/>
    </decision>
    <decision expression="#{entityManager.createQuery(&quot;SELECT COUNT(*) FROM ProcessoParteExpediente AS ppe JOIN ppe.processoExpediente AS pe WHERE ppe.processoJudicial.idProcessoTrf = :idProcessoTrf AND pe.tipoProcessoDocumento.idTipoProcessoDocumento = 34 AND pe.meioExpedicaoExpediente = 'M' AND ppe.fechado = false&quot;).setParameter(&quot;idProcessoTrf&quot;, tramitacaoProcessualService.recuperaProcesso().idProcessoTrf).getSingleResult() &gt; 0 ? '(SG) Existe registro do processo na tarefa de aguardar OJ?' : '(SG) Junção em controle de prazos de ofícios'}" name="(SG) É mandado?">
        <transition to="(SG) Junção em controle de prazos de ofícios" name="(SG) Junção em controle de prazos de ofícios"/>
        <transition to="(SG) Existe registro do processo na tarefa de aguardar OJ?" name="(SG) Existe registro do processo na tarefa de aguardar OJ?"/>
    </decision>
    <decision expression="#{entityManager.createQuery(&quot;SELECT COUNT(*) FROM SituacaoProcesso AS s WHERE s.nomeTarefa = '(SG) Ofício pendente de cumprimento pelo OJ - AGUARDAR' AND s.processoTrf.idProcessoTrf = :idProcessoTrf&quot;).setParameter(&quot;idProcessoTrf&quot;, tramitacaoProcessualService.recuperaProcesso().idProcessoTrf).getSingleResult() &gt; 0 ? '(SG) Separação em ofício com ou sem prazo' : '(SG) Ofício pendente de cumprimento pelo OJ - AGUARDAR'}" name="(SG) Existe registro do processo na tarefa de aguardar OJ?">
        <transition to="(SG) Ofício pendente de cumprimento pelo OJ - AGUARDAR" name="(SG) Ofício pendente de cumprimento pelo OJ - AGUARDAR"/>
        <transition to="(SG) Separação em ofício com ou sem prazo" name="(SG) Separação em ofício com ou sem prazo"/>
    </decision>
    <task-node end-tasks="true" name="(SG) Ofício pendente de cumprimento pelo OJ - AGUARDAR">
        <task name="(SG) Ofício pendente de cumprimento pelo OJ - AGUARDAR" swimlane="Secretaria">
            <controller>
                <variable name="aviso1" mapped-name="textAlert:aviso1" access="read,write"/>
                <variable name="movimentacaoLote" mapped-name="movimentarLote:movimentacaoLote" access="read,write"/>
            </controller>
        </task>
        <description><![CDATA[*Variáveis*

1. Variável: aviso1
   Label: O processo encontra-se com ofício pendente de cumprimento pela Central de Mandados. Após o cumprimento, clique na próxima ação abaixo.
   Escrita: Sim
   Obrig.: Não
   Tipo: Aviso

2. Variável: movimentacaoLote
   Label:
   Escrita: Sim
   Obrig.: Não
   Tipo: Habilitar Movimentação em Lote]]></description>
        <transition to="(SG) Junção em controle de prazos de ofícios" name="Cancelar e sair da tarefa"/>
        <transition to="Nó de Desvio - (SG) Controle de prazos de ofícios" name="Nó de Desvio - (SG) Controle de prazos de ofícios">
            <condition expression="#{true}"/>
        </transition>
        <transition to="(SG) Separação em ofício com ou sem prazo" name="Verificar existência de prazo"/>
        <event type="task-create">
            <action expression="#{tramitacaoProcessualService.gravaVariavelTarefa('mostrarBotaoGravarNoFluxo', false)}"/>
        </event>
        <event type="task-end">
            <action expression="#{tramitacaoProcessualService.apagaVariavelTarefa('mostrarBotaoGravarNoFluxo')}"/>
        </event>
    </task-node>
    <fork name="(SG) Separação em ofício com ou sem prazo">
        <transition to="(SG) Existe prazo de ofício em aberto?" name="(SG) Existe prazo de ofício em aberto?"/>
        <transition to="(SG) Existe ofício sem prazo?" name="(SG) Existe ofício sem prazo?"/>
    </fork>
    <decision expression="#{entityManager.createQuery(&quot;SELECT COUNT(*) FROM ProcessoParteExpediente AS ppe JOIN ppe.processoExpediente AS pe WHERE ppe.processoJudicial.idProcessoTrf = :idProcessoTrf AND pe.tipoProcessoDocumento.idTipoProcessoDocumento = 34 AND pe.meioExpedicaoExpediente IN ('E','C','M') AND ppe.dtCienciaParte IS NOT NULL AND ppe.fechado = false AND ppe.tipoPrazo &lt;&gt; 'S'&quot;).setParameter(&quot;idProcessoTrf&quot;, tramitacaoProcessualService.recuperaProcesso().idProcessoTrf).getSingleResult() &gt; 0 ? '(SG) Existe registro do processo na tarefa com prazo?' : '(SG) Junção em ofício com ou sem prazo'}" name="(SG) Existe prazo de ofício em aberto?">
        <transition to="(SG) Junção em ofício com ou sem prazo" name="(SG) Junção em ofício com ou sem prazo"/>
        <transition to="(SG) Existe registro do processo na tarefa com prazo?" name="(SG) Existe registro do processo na tarefa com prazo?"/>
    </decision>
    <decision expression="#{entityManager.createQuery(&quot;SELECT COUNT(*) FROM SituacaoProcesso AS s WHERE s.nomeTarefa = '(SG) Ofício com prazo em curso - AGUARDAR' AND s.processoTrf.idProcessoTrf = :idProcessoTrf&quot;).setParameter(&quot;idProcessoTrf&quot;, tramitacaoProcessualService.recuperaProcesso().idProcessoTrf).getSingleResult() &gt; 0 ? '(SG) Junção em ofício com ou sem prazo' : '(SG) Ofício com prazo em curso - AGUARDAR'}" name="(SG) Existe registro do processo na tarefa com prazo?">
        <transition to="(SG) Ofício com prazo em curso - AGUARDAR" name="(SG) Ofício com prazo em curso - AGUARDAR"/>
        <transition to="(SG) Junção em ofício com ou sem prazo" name="(SG) Junção em ofício com ou sem prazo"/>
    </decision>
    <task-node end-tasks="true" name="(SG) Ofício com prazo em curso - AGUARDAR">
        <task name="(SG) Ofício com prazo em curso - AGUARDAR" swimlane="Secretaria">
            <controller>
                <variable name="aviso1" mapped-name="textAlert:aviso1" access="read,write"/>
                <variable name="movimentacaoLote" mapped-name="movimentarLote:movimentacaoLote" access="read,write"/>
            </controller>
        </task>
        <description><![CDATA[*Variáveis*

1. Variável: aviso1
   Label: O processo contém ofício com prazo em curso. Após o fechamento de todos os prazos que estão abertos dos ofícios, o processo será encaminhado automaticamente para tarefa "(SG) Ofício com prazo decorrido".
   Escrita: Sim
   Obrig.: Não
   Tipo: Aviso

2. Variável: movimentacaoLote
   Label:
   Escrita: Sim
   Obrig.: Não
   Tipo: Habilitar Movimentação em Lote]]></description>
        <transition to="Nó de Desvio - (SG) Controle de prazos de ofícios" name="Nó de Desvio - (SG) Controle de prazos de ofícios">
            <condition expression="#{true}"/>
        </transition>
        <transition to="(SG) Junção em ofício com ou sem prazo" name="Cancelar e sair da tarefa"/>
        <transition to="(SG) Ainda existe prazo de ofício em aberto?" name="Verificar existência de prazo">
            <condition expression="#{true}"/>
        </transition>
        <event type="task-create">
            <action expression="#{tramitacaoProcessualService.gravaVariavelTarefa('frameDefaultLeavingTransition', 'Verificar existência de prazo')}"/>
            <action expression="#{tramitacaoProcessualService.gravaVariavelTarefa('pje:aguardaPeticao', true)}"/>
            <action expression="#{tramitacaoProcessualService.gravaVariavelTarefa('mostrarBotaoGravarNoFluxo', false)}"/>
            <action expression="#{tramitacaoProcessualService.gravaVariavelTarefa('pje:aguardaCiencia', 'true')}"/>
        </event>
        <event type="task-end">
            <action expression="#{tramitacaoProcessualService.apagaVariavelTarefa('pje:aguardaPeticao')}"/>
            <action expression="#{tramitacaoProcessualService.apagaVariavelTarefa('mostrarBotaoGravarNoFluxo')}"/>
            <action expression="#{tramitacaoProcessualService.apagaVariavelTarefa('frameDefaultLeavingTransition')}"/>
            <action expression="#{tramitacaoProcessualService.apagaVariavelTarefa('pje:aguardaCiencia')}"/>
        </event>
    </task-node>
    <decision expression="#{entityManager.createQuery(&quot;SELECT COUNT(*) FROM ProcessoParteExpediente AS ppe JOIN ppe.processoExpediente AS pe WHERE ppe.processoJudicial.idProcessoTrf = :idProcessoTrf AND pe.tipoProcessoDocumento.idTipoProcessoDocumento = 34 AND pe.meioExpedicaoExpediente IN ('E','C','M') AND ppe.fechado = false AND ppe.tipoPrazo &lt;&gt; 'S'&quot;).setParameter(&quot;idProcessoTrf&quot;, tramitacaoProcessualService.recuperaProcesso().idProcessoTrf).getSingleResult() &gt; 0 ? '(SG) Ofício com prazo em curso - AGUARDAR' : '(SG) Ofício com prazo decorrido - ANALISAR'}" name="(SG) Ainda existe prazo de ofício em aberto?">
        <transition to="(SG) Ofício com prazo em curso - AGUARDAR" name="(SG) Ofício com prazo em curso - AGUARDAR"/>
        <transition to="(SG) Ofício com prazo decorrido - ANALISAR" name="(SG) Ofício com prazo decorrido - ANALISAR"/>
    </decision>
    <task-node end-tasks="true" name="(SG) Ofício com prazo decorrido - ANALISAR">
        <task name="(SG) Ofício com prazo decorrido - ANALISAR" swimlane="Secretaria">
            <controller>
                <variable name="aviso1" mapped-name="textAlert:aviso1" access="read,write"/>
                <variable name="movimentacaoLote" mapped-name="movimentarLote:movimentacaoLote" access="read,write"/>
            </controller>
        </task>
        <description><![CDATA[*Variáveis*

1. Variável: aviso1
   Label: Ofícios com prazos decorridos. Clique na próxima ação para prosseguir.
   Escrita: Sim
   Obrig.: Não
   Tipo: Aviso

2. Variável: movimentacaoLote
   Label:
   Escrita: Sim
   Obrig.: Não
   Tipo: Habilitar Movimentação em Lote]]></description>
        <transition to="Nó de Desvio - (SG) Controle de prazos de ofícios" name="Nó de Desvio - (SG) Controle de prazos de ofícios">
            <condition expression="#{true}"/>
        </transition>
        <transition to="(SG) Junção em ofício com ou sem prazo" name="Cancelar e sair da tarefa"/>
        <event type="task-create">
            <action expression="#{tramitacaoProcessualService.gravaVariavelTarefa('mostrarBotaoGravarNoFluxo', false)}"/>
        </event>
        <event type="task-end">
            <action expression="#{tramitacaoProcessualService.apagaVariavelTarefa('mostrarBotaoGravarNoFluxo')}"/>
        </event>
    </task-node>
    <decision expression="#{entityManager.createQuery(&quot;SELECT COUNT(*) FROM ProcessoParteExpediente AS ppe JOIN ppe.processoExpediente AS pe WHERE ppe.processoJudicial.idProcessoTrf = :idProcessoTrf AND pe.tipoProcessoDocumento.idTipoProcessoDocumento = 34 AND pe.meioExpedicaoExpediente IN ('E','C', 'M') AND ppe.dtCienciaParte IS NOT NULL AND ppe.fechado = false AND ppe.tipoPrazo = 'S'&quot;).setParameter(&quot;idProcessoTrf&quot;, tramitacaoProcessualService.recuperaProcesso().idProcessoTrf).getSingleResult() &gt; 0 ? '(SG) Existe registro do processo na tarefa sem prazo?' : '(SG) Junção em ofício com ou sem prazo'}" name="(SG) Existe ofício sem prazo?">
        <transition to="(SG) Junção em ofício com ou sem prazo" name="(SG) Junção em ofício com ou sem prazo"/>
        <transition to="(SG) Existe registro do processo na tarefa sem prazo?" name="(SG) Existe registro do processo na tarefa sem prazo?"/>
    </decision>
    <decision expression="#{entityManager.createQuery(&quot;SELECT COUNT(*) FROM SituacaoProcesso AS s WHERE s.nomeTarefa = '(SG) Ofício sem prazo pendente de resposta - AGUARDAR' AND s.processoTrf.idProcessoTrf = :idProcessoTrf&quot;).setParameter(&quot;idProcessoTrf&quot;, tramitacaoProcessualService.recuperaProcesso().idProcessoTrf).getSingleResult() &gt; 0 ? '(SG) Junção em ofício com ou sem prazo' : '(SG) Ofício sem prazo pendente de resposta - AGUARDAR'}" name="(SG) Existe registro do processo na tarefa sem prazo?">
        <transition to="(SG) Ofício sem prazo pendente de resposta - AGUARDAR" name="(SG) Ofício sem prazo pendente de resposta - AGUARDAR"/>
        <transition to="(SG) Junção em ofício com ou sem prazo" name="(SG) Junção em ofício com ou sem prazo"/>
    </decision>
    <task-node end-tasks="true" name="(SG) Ofício sem prazo pendente de resposta - AGUARDAR">
        <task name="(SG) Ofício sem prazo pendente de resposta - AGUARDAR" swimlane="Secretaria">
            <controller>
                <variable name="aviso1" mapped-name="textAlert:aviso1" access="read,write"/>
                <variable name="movimentacaoLote" mapped-name="movimentarLote:movimentacaoLote" access="read,write"/>
            </controller>
        </task>
        <description><![CDATA[*Variáveis*

1. Variável: aviso1
   Label: O processo encontra-se com ofício expedido sem prazo. Mantenha-o nesta tarefa caso queira aguardar a resposta ou clique na próxima ação abaixo para cancelar e sair da tarefa.
   Escrita: Sim
   Obrig.: Não
   Tipo: Aviso

2. Variável: movimentacaoLote
   Label:
   Escrita: Sim
   Obrig.: Não
   Tipo: Habilitar Movimentação em Lote]]></description>
        <transition to="Nó de Desvio - (SG) Controle de prazos de ofícios" name="Nó de Desvio - (SG) Controle de prazos de ofícios">
            <condition expression="#{true}"/>
        </transition>
        <transition to="(SG) Junção em ofício com ou sem prazo" name="Cancelar e sair da tarefa"/>
        <transition to="(SG) Existe ofício sem prazo ainda aberto?" name="(SG) Existe ofício sem prazo ainda aberto?">
            <condition expression="#{true}"/>
        </transition>
        <event type="task-create">
            <action expression="#{tramitacaoProcessualService.gravaVariavelTarefa('mostrarBotaoGravarNoFluxo', false)}"/>
            <action expression="#{tramitacaoProcessualService.gravaVariavelTarefa('frameDefaultLeavingTransition', '(SG) Existe ofício sem prazo ainda aberto?')}"/>
            <action name="upd" expression="#{tramitacaoProcessualService.gravaVariavelTarefa('pje:aguardaPeticao', true)}"/>
            <action expression="#{tramitacaoProcessualService.gravaVariavelTarefa('pje:aguardaCiencia', 'true')}"/>
        </event>
        <event type="task-end">
            <action expression="#{tramitacaoProcessualService.apagaVariavelTarefa('mostrarBotaoGravarNoFluxo')}"/>
            <action expression="#{tramitacaoProcessualService.apagaVariavelTarefa('pje:aguardaPeticao')}"/>
            <action expression="#{tramitacaoProcessualService.apagaVariavelTarefa('frameDefaultLeavingTransition')}"/>
            <action expression="#{tramitacaoProcessualService.apagaVariavelTarefa('pje:aguardaCiencia')}"/>
        </event>
    </task-node>
    <decision expression="#{entityManager.createQuery(&quot;SELECT COUNT(*) FROM ProcessoParteExpediente AS ppe JOIN ppe.processoExpediente AS pe WHERE ppe.processoJudicial.idProcessoTrf = :idProcessoTrf AND pe.tipoProcessoDocumento.idTipoProcessoDocumento = 34 AND pe.meioExpedicaoExpediente IN ('E','C','M') AND ppe.fechado = false AND ppe.tipoPrazo = 'S'&quot;).setParameter(&quot;idProcessoTrf&quot;, tramitacaoProcessualService.recuperaProcesso().idProcessoTrf).getSingleResult() &gt; 0 ? '(SG) Ofício sem prazo e fechado - ANALISAR' : '(SG) Ofício sem prazo pendente de resposta - AGUARDAR'}" name="(SG) Existe ofício sem prazo ainda aberto?">
        <transition to="(SG) Ofício sem prazo e fechado - ANALISAR" name="(SG) Ofício sem prazo e fechado - ANALISAR"/>
        <transition to="(SG) Ofício sem prazo pendente de resposta - AGUARDAR" name="(SG) Ofício sem prazo pendente de resposta - AGUARDAR"/>
    </decision>
    <task-node end-tasks="true" name="(SG) Ofício sem prazo e fechado - ANALISAR">
        <task name="(SG) Ofício sem prazo e fechado - ANALISAR" swimlane="Secretaria">
            <controller>
                <variable name="aviso1" mapped-name="textAlert:aviso1" access="read,write"/>
                <variable name="movimentacaoLote" mapped-name="movimentarLote:movimentacaoLote" access="read,write"/>
            </controller>
        </task>
        <description><![CDATA[*Variáveis*

1. Variável: aviso1
   Label: Ofícios com prazos fechados. Clique na próxima ação para prosseguir.
   Escrita: Sim
   Obrig.: Não
   Tipo: Aviso

2. Variável: movimentacaoLote
   Label:
   Escrita: Sim
   Obrig.: Não
   Tipo: Aviso]]></description>
        <transition to="(SG) Junção em ofício com ou sem prazo" name="Cancelar e sair da tarefa"/>
        <transition to="Nó de Desvio - (SG) Controle de prazos de ofícios" name="Nó de Desvio - (SG) Controle de prazos de ofícios">
            <condition expression="#{true}"/>
        </transition>
    </task-node>
    <join name="(SG) Junção em ofício com ou sem prazo">
        <transition to="(SG) Junção em controle de prazos de ofícios" name="(SG) Junção em controle de prazos de ofícios"/>
    </join>
    <join name="(SG) Junção em controle de prazos de ofícios">
        <transition to="(SG) Apagar variáveis do fluxo" name="(SG) Apagar variáveis do fluxo"/>
    </join>
    <node name="(SG) Apagar variáveis do fluxo">
        <transition to="Término" name="Término"/>
        <event type="node-enter">
            <action expression="#{tramitacaoProcessualService.apagaVariavel('comunicacaoProcessualAction:idsExpedientes')}"/>
        </event>
    </node>
    <end-state name="Término"/>
    <task-node end-tasks="true" name="Nó de Desvio - (SG) Controle de prazos de ofícios">
        <task name="Nó de Desvio - (SG) Controle de prazos de ofícios" swimlane="Nó de Desvio - (SG) Controle de prazos de ofícios"/>
        <transition to="Término" name="Término"/>
        <transition to="(SG) Ofício pendente de devolução do AR - AGUARDAR" name="(SG) Ofício pendente de devolução do AR - AGUARDAR"/>
        <transition to="(SG) Ofício pendente de devolução do AR - REGISTRAR" name="(SG) Ofício pendente de devolução do AR - REGISTRAR"/>
        <transition to="(SG) Ofício com prazo em curso - AGUARDAR" name="(SG) Ofício com prazo em curso - AGUARDAR"/>
        <transition to="(SG) Ofício com prazo decorrido - ANALISAR" name="(SG) Ofício com prazo decorrido - ANALISAR"/>
        <transition to="(SG) Ofício pendente de cumprimento pelo OJ - AGUARDAR" name="(SG) Ofício pendente de cumprimento pelo OJ - AGUARDAR"/>
        <transition to="(SG) Ofício sem prazo pendente de resposta - AGUARDAR" name="(SG) Ofício sem prazo pendente de resposta - AGUARDAR"/>
        <transition to="(SG) Ofício sem prazo e fechado - ANALISAR" name="(SG) Ofício sem prazo e fechado - ANALISAR"/>
        <transition to="(SG) Ofício pendente de confirmação do recebimento - REGISTRAR" name="(SG) Ofício pendente de confirmação do recebimento - REGISTRAR"/>
    </task-node>  
    <!-- PROCESS-EVENTS -->
    <event type="node-enter">
        <script>br.com.infox.ibpm.util.JbpmEvents.raiseEvent(executionContext)</script>
    </event>
    <event type="superstate-leave">
        <script>br.com.infox.ibpm.util.JbpmEvents.raiseEvent(executionContext)</script>
    </event>
    <event type="subprocess-end">
        <script>br.com.infox.ibpm.util.JbpmEvents.raiseEvent(executionContext)</script>
    </event>
    <event type="node-leave">
        <script>br.com.infox.ibpm.util.JbpmEvents.raiseEvent(executionContext)</script>
    </event>
    <event type="before-signal">
        <script>br.com.infox.ibpm.util.JbpmEvents.raiseEvent(executionContext)</script>
    </event>
    <event type="superstate-enter">
        <script>br.com.infox.ibpm.util.JbpmEvents.raiseEvent(executionContext)</script>
    </event>
    <event type="process-start">
        <script>br.com.infox.ibpm.util.JbpmEvents.raiseEvent(executionContext)</script>
    </event>
    <event type="transition">
        <script>br.com.infox.ibpm.util.JbpmEvents.raiseEvent(executionContext)</script>
    </event>
    <event type="process-end">
        <script>br.com.infox.ibpm.util.JbpmEvents.raiseEvent(executionContext)</script>
    </event>
    <event type="task-end">
        <script>br.com.infox.ibpm.util.JbpmEvents.raiseEvent(executionContext)</script>
    </event>
    <event type="task-start">
        <script>br.com.infox.ibpm.util.JbpmEvents.raiseEvent(executionContext)</script>
    </event>
    <event type="subprocess-created">
        <script>br.com.infox.ibpm.util.JbpmEvents.raiseEvent(executionContext)</script>
    </event>
    <event type="after-signal">
        <script>br.com.infox.ibpm.util.JbpmEvents.raiseEvent(executionContext)</script>
    </event>
    <event type="task-assign">
        <script>br.com.infox.ibpm.util.JbpmEvents.raiseEvent(executionContext)</script>
    </event>
    <event type="task-create">
        <script>br.com.infox.ibpm.util.JbpmEvents.raiseEvent(executionContext)</script>
    </event>
    <event type="timer">
        <script>br.com.infox.ibpm.util.JbpmEvents.raiseEvent(executionContext)</script>
    </event>  
    <!-- ACTIONS --> 
</process-definition>